Metadata-Version: 2.1
Name: odoo-addon-test_queue_job
Version: 19.0.1.0.1
Requires-Dist: odoo-addon-queue_job==19.0.*
Requires-Dist: odoo==19.0.*
Summary: Queue Job Tests
Home-page: https://github.com/OCA/queue
License: LGPL-3
Author: Camptocamp,Odoo Community Association (OCA)
Author-email: support@odoo-community.org
Classifier: Programming Language :: Python
Classifier: Framework :: Odoo
Classifier: Framework :: Odoo :: 19.0
Classifier: License :: OSI Approved :: GNU Lesser General Public License v3 (LGPLv3)
